papyra/__init__.py
papyra/_envelope.py
papyra/actor.py
papyra/address.py
papyra/audit.py
papyra/context.py
papyra/events.py
papyra/exceptions.py
papyra/hooks.py
papyra/logging.py
papyra/mailbox.py
papyra/monkay.py
papyra/py.typed
papyra/ref.py
papyra/serializers.py
papyra/supervision.py
papyra/supervisor.py
papyra/system.py
papyra/typing.py
papyra/cli/__init__.py
papyra/cli/app.py
papyra/cli/doctor/__init__.py
papyra/cli/doctor/app.py
papyra/cli/inspect/__init__.py
papyra/cli/inspect/app.py
papyra/cli/metrics/__init__.py
papyra/cli/metrics/app.py
papyra/cli/persistence/__init__.py
papyra/cli/persistence/app.py
papyra/conf/__init__.py
papyra/conf/global_settings.py
papyra/contrib/__init__.py
papyra/contrib/asgi/__ini__.py
papyra/contrib/asgi/endpoints.py
papyra/contrib/asgi/lifesycle.py
papyra/contrib/asgi/types.py
papyra/contrib/fastapi/__init__.py
papyra/contrib/fastapi/integration.py
papyra/contrib/lilya/__init__.py
papyra/contrib/lilya/integration.py
papyra/contrib/ravyn/__init__.py
papyra/contrib/ravyn/integration.py
papyra/contrib/starlette/__init__.py
papyra/contrib/starlette/integration.py
papyra/persistence/__init__.py
papyra/persistence/_retention.py
papyra/persistence/_utils.py
papyra/persistence/base.py
papyra/persistence/contract.py
papyra/persistence/json.py
papyra/persistence/metrics.py
papyra/persistence/models.py
papyra/persistence/startup.py
papyra/persistence/backends/__init__.py
papyra/persistence/backends/memory.py
papyra/persistence/backends/redis.py
papyra/persistence/backends/retention.py
papyra/persistence/backends/rotating.py
papyra/protocols/__init__.py
papyra/protocols/logging.py
papyra/protocols/serializer.py
papyra/utils/__init__.py
papyra/utils/logging.py
papyra-0.1.0.dist-info/METADATA
papyra-0.1.0.dist-info/WHEEL
papyra-0.1.0.dist-info/entry_points.txt
papyra-0.1.0.dist-info/licenses/LICENSE
papyra-0.1.0.dist-info/RECORD
