Metadata-Version: 2.4
Name: papyra
Version: 0.1.0
Summary: The async actor model you didn't know you needed
Project-URL: Homepage, https://github.com/dymmond/papyra
Project-URL: Documentation, https://papyra.dymmond.com
Project-URL: Changelog, https://papyra.dymmond.com/release-notes/
Project-URL: Funding, https://github.com/sponsors/tarsil
Project-URL: Source, https://github.com/dymmond/papyra
Author-email: Tiago Silva <tiago@tarsild.io>
License-File: LICENSE
Keywords: actor,actor-system,asgi,async,concurrency,distributed-systems,papyra
Classifier: Development Status :: 4 - Beta
Classifier: Environment :: Web Environment
Classifier: Framework :: AnyIO
Classifier: Framework :: AsyncIO
Classifier: Intended Audience :: Developers
Classifier: Intended Audience :: Information Technology
Classifier: Intended Audience :: System Administrators
Classifier: License :: OSI Approved :: BSD License
Classifier: Operating System :: OS Independent
Classifier: Programming Language :: Python
Classifier: Programming Language :: Python :: 3
Classifier: Programming Language :: Python :: 3 :: Only
Classifier: Programming Language :: Python :: 3.10
Classifier: Programming Language :: Python :: 3.11
Classifier: Programming Language :: Python :: 3.12
Classifier: Programming Language :: Python :: 3.13
Classifier: Programming Language :: Python :: 3.14
Classifier: Topic :: Internet
Classifier: Topic :: Internet :: WWW/HTTP
Classifier: Topic :: Internet :: WWW/HTTP :: HTTP Servers
Classifier: Topic :: Software Development
Classifier: Topic :: Software Development :: Libraries
Classifier: Topic :: Software Development :: Libraries :: Application Frameworks
Classifier: Topic :: Software Development :: Libraries :: Python Modules
Classifier: Typing :: Typed
Requires-Python: >=3.10
Requires-Dist: anyio>=4.12.0
Requires-Dist: sayer>=0.7.5
Provides-Extra: redis
Requires-Dist: redis>=7.1.0; extra == 'redis'
Provides-Extra: testing
Requires-Dist: autoflake<3.0.0,>=2.0.2; extra == 'testing'
Requires-Dist: black<25.0,==24.1.1; extra == 'testing'
Requires-Dist: fastapi; extra == 'testing'
Requires-Dist: httpx; extra == 'testing'
Requires-Dist: ipdb; extra == 'testing'
Requires-Dist: isort<6.0.0,>=5.12.0; extra == 'testing'
Requires-Dist: pytest-cov<5.0.0,>=4.0.0; extra == 'testing'
Requires-Dist: pytest<9.0.0,>=7.2.2; extra == 'testing'
Requires-Dist: ravyn; extra == 'testing'
